alpensia/__init__.py
alpensia/alpen.py
alpensia-0.1.1.dist-info/METADATA
alpensia-0.1.1.dist-info/WHEEL
alpensia-0.1.1.dist-info/top_level.txt
alpensia-0.1.1.dist-info/RECORD
