Metadata-Version: 2.1
Name: alpensia
Version: 0.1.1
Summary: Alpensia project is in 441.
Home-page: https://github.com/youngshk/alpensia
Author: Awesome Soul
Author-email: ynsnkim@gmail.com
License: MIT
Platform: UNKNOWN
Classifier: License :: OSI Approved :: MIT License
Classifier: Programming Language :: Python
Classifier: Programming Language :: Python :: 3
Classifier: Programming Language :: Python :: 3.6
Classifier: Programming Language :: Python :: Implementation :: CPython
Classifier: Programming Language :: Python :: Implementation :: PyPy
Requires-Python: >=3.6.0
Requires-Dist: matplotlib
